stash/__init__.py
stash/cli.py
stash/context.py
stash/store.py
stash_rlm-0.1.4.dist-info/METADATA
stash_rlm-0.1.4.dist-info/WHEEL
stash_rlm-0.1.4.dist-info/entry_points.txt
stash_rlm-0.1.4.dist-info/licenses/LICENSE
stash_rlm-0.1.4.dist-info/RECORD
