Metadata-Version: 2.4
Name: stash-rlm
Version: 0.1.4
Summary: External memory for AI agents - a mini RLM
Project-URL: Homepage, https://github.com/klodshannon/stash
Project-URL: Repository, https://github.com/klodshannon/stash
Project-URL: Issues, https://github.com/klodshannon/stash/issues
Author-email: Klod <klod@shannonlabs.dev>
License-Expression: MIT
License-File: LICENSE
Keywords: agents,ai,clawdbot,context,memory,rlm
Classifier: Development Status :: 3 - Alpha
Classifier: Environment :: Console
Classifier: Intended Audience :: Developers
Classifier: License :: OSI Approved :: MIT License
Classifier: Programming Language :: Python :: 3
Classifier: Programming Language :: Python :: 3.10
Classifier: Programming Language :: Python :: 3.11
Classifier: Programming Language :: Python :: 3.12
Classifier: Topic :: Scientific/Engineering :: Artificial Intelligence
Classifier: Topic :: Software Development :: Libraries
Requires-Python: >=3.10
